cooklang_py/__init__.py
cooklang_py/base_objects.py
cooklang_py/const.py
cooklang_py/quantity.py
cooklang_py/recipe.py
cooklang_py/utils.py
cooklang_py-0.3.2.dist-info/licenses/LICENSE.md
cooklang_py-0.3.2.dist-info/WHEEL
cooklang_py-0.3.2.dist-info/METADATA
cooklang_py-0.3.2.dist-info/RECORD
