Metadata-Version: 2.4
Name: cooklang-py
Version: 0.3.2
Summary: Python Parser for Cooklang
Author: Dan Shernicoff
Author-email: Dan Shernicoff <dan@brassnet.biz>
License-Expression: MIT
License-File: LICENSE.md
Requires-Dist: python-frontmatter==1.1.0
Requires-Python: >=3.10
Project-URL: Repository, https://github.com/brass75/cooklang-py
Project-URL: cooklang, https://cooklang.org
Project-URL: documentation, https://cooklang-py.readthedocs.io/
Project-URL: homepage, https://github.com/brass75/cooklang-py
